termgpt/__init__.py
termgpt/termgpt.py
termigpt-0.1.1.dist-info/METADATA
termigpt-0.1.1.dist-info/WHEEL
termigpt-0.1.1.dist-info/entry_points.txt
termigpt-0.1.1.dist-info/RECORD
